venafi_csp/__init__.py
venafi_csp/container_init_command.py
venafi_csp/jarsigner_sign_command.py
venafi_csp/jarsigner_verify_command.py
venafi_csp/signtool_sign_command.py
venafi_csp/signtool_verify_command.py
venafi_csp/utils.py
venafi_csp/version_command.py
venafi_csp/support/version.txt
venafi_csp/support/java/IsJre64Bit.class
venafi_csp-2.0.2.dist-info/LICENSE
venafi_csp-2.0.2.dist-info/METADATA
venafi_csp-2.0.2.dist-info/WHEEL
venafi_csp-2.0.2.dist-info/entry_points.txt
venafi_csp-2.0.2.dist-info/top_level.txt
venafi_csp-2.0.2.dist-info/RECORD
