Metadata-Version: 2.1
Name: venafi-csp
Version: 2.0.2
Summary: Python Package that provides abstracted library access for various code signing clients to Venafi CodeSign Protect resources
Author-email: Qensus <venafi.oss@qensus.com>
Project-URL: Homepage, https://github.com/qensus-labs/venafi-csp-lib-python
Classifier: License :: OSI Approved :: Apache Software License
Classifier: Operating System :: OS Independent
Classifier: Programming Language :: Python :: 3
Requires-Python: >=3.8
License-File: LICENSE
Requires-Dist: envparse <0.3,>=0.2.0
